README.md
ex1.py
ex2.py
setup.py
Package_Calculator/__init__.py
Package_Calculator/calculator.py
Package_Calculator/__pycache__/__init__.cpython-36.pyc
Package_Calculator/__pycache__/calculator.cpython-36.pyc
Package_Test/Test.py
Package_Test/__init__.py
Simple_Complex_Calulator.egg-info/PKG-INFO
Simple_Complex_Calulator.egg-info/SOURCES.txt
Simple_Complex_Calulator.egg-info/dependency_links.txt
Simple_Complex_Calulator.egg-info/top_level.txt