Metadata-Version: 1.1
Name: Simple-Complex-Calulator
Version: 0.1
Summary: Réaliser les différentes opérations élémentaires entre 2 nombres complexes : addition,différence,multiplication,division
Home-page: UNKNOWN
Author: Benoit-Jomain
Author-email: benoit.jomain@cpe.fr
License: UNKNOWN
Platform: UNKNOWN
Classifier: Programming Language :: Python :: 3
